{"1":["Los Tacos Azules（ロス・タコス・アスーレス）","東京","世田谷区三軒茶屋"],"2":["みよし屋","東京","品川区西中延"],"3":["HOBO TACOS（ホーボータコス）","東京","中野区新中野"],"4":["北出TACOS グランスタ東京店","東京","千代田区東京駅"],"5":["LAS DOS CARAS","東京","渋谷区原宿・神宮前"],"6":["TACO FANATICO（タコ ファナティコ）","東京","目黒区中目黒"],"7":["Chelas（チェラス）","東京","世田谷区尾山台"],"8":["墨国回転鶏食堂 ルクアイーレ店","大阪","北区梅田・大阪駅"],"9":["墨国回転鶏料理 天満本店","大阪","北区天満"],"10":["プーマ・アステカ","大阪","浪速区難波"],"11":["TACO FANATICO 久屋大通店","名古屋","中区久屋大通"],"12":["Tacomia（タコミア）","福岡","中央区大手門"],"13":["dos tacos yasaka（ドス タコス ヤサカ）","京都","東山区八坂神社前"],"14":["ELtope（エルトペ）","北海道","札幌中央区大通"],"15":["LUKE TACOS（ルークタコス）","沖縄","中頭郡嘉手納町"],"16":["BORRACHOS（ボラーチョス）","広島","中区薬研堀"],"17":["Tacos 3hermanos 原宿","東京","渋谷区神宮前"],"18":["Tacos 3hermanos 恵比寿","東京","渋谷区恵比寿"],"19":["Tacos 3hermanos 浅草","東京","台東区浅草"],"20":["Tacos 3hermanos 下北沢","東京","世田谷区北沢"],"21":["OXOMOCO","東京","渋谷区広尾"],"22":["Tortilla Club TORTILLERIA","東京","渋谷区代々木上原"],"23":["タコスショップ キチジョウジ","東京","武蔵野市吉祥寺本町"],"24":["FONDA DE LA MADRUGADA","東京","渋谷区原宿"],"25":["AMENRO LA FIESTA","東京","港区六本木"],"26":["カサ・デ・サラサ","東京","渋谷区渋谷"],"27":["Don Chava","東京","千代田区水道橋"],"28":["覆面タコス","東京","台東区浅草"],"29":["TEXMEX FACTORY 渋谷公園通り店","東京","渋谷区神宮前"],"30":["EL BORRACHO","東京","渋谷区恵比寿"],"31":["Taco Bell 渋谷道玄坂店","東京","渋谷区道玄坂"],"32":["Taco Bell 東京ドームシティ店","東京","文京区後楽"],"33":["Guzman y Gomez 原宿店","東京","渋谷区神宮前"],"34":["Guzman y Gomez 渋谷店","東京","渋谷区渋谷"],"35":["LA ESQUINA","東京","中央区銀座"],"36":["エル・リンコン・デ・サム","東京","杉並区高円寺"],"37":["MEXICAN DINING AVOCADO HOUSE","大阪","浪速区難波"],"38":["TACOS EL NOPAL","大阪","淀巜区十三"],"39":["campe-chano","大阪","中央区心斎橋"],"40":["タコスと肴と酒 タコフィニ","大阪","北区梅田"],"41":["EL PANCHO","大阪","阿倍野区天王寺"],"42":["CASA DE SARASA 大阪店","大阪","中央区南船場"],"43":["Guzman y Gomez なんばパークス店","大阪","浪速区難波"],"44":["Taco Bell 道頓堀店","大阪","中央区道頓堀"],"45":["メキシカーナ","大阪","中央区天満橋"],"46":["JERRY","名古屋","昭和区鶴舞"],"47":["Sayulita","名古屋","中区大須"],"48":["Hot Spice MUCHO CHICKEN","名古屋","中区栄"],"49":["Guzman y Gomez 名古屋パルコ店","名古屋","中区栄"],"50":["オラレ","京都","中京区四条烏丸"],"51":["ロティーチキン&ジャッキータコス","京都","中京区四条"],"52":["チャーリー多幸寿 本店","沖縄","沖縄市"],"53":["キングタコス 金武本店","沖縄","金武町"],"54":["キングタコス 長田店","沖縄","那覇市"],"55":["タコス専門店 メキシコ","沖縄","宜野湾市"],"56":["SENOR TACO","沖縄","沖縄市"],"57":["BORRACHOS","沖縄","那覇市"],"58":["ランチョエルパソ by ESTARICO","北海道","札幌市中央区すすきの"],"59":["唸るタコス","福岡","福岡市中央区大濠"],"60":["瘉球多幸寿 福岡店","福岡","福岡市博多区"],"61":["La Fiesta","神奈川","横浜市中区元町"],"62":["Guzman y Gomez 横浜店","神奈川","横浜市西区"],"63":["Umacchi Tacos","兵庫","神戸市中央区三宮"],"64":["Don Tacos","宮城","仙台市青葉区木町通"],"65":["Taco Bell 渋谷道玄坂店","東京","渋谷区道玄坂"],"66":["Taco Bell 東京ドームシティ店","東京","文京区後楽"],"67":["LA ESQUINA 銀座","東京","中央区銀座"],"68":["エル・リンコン・デ・サム 高円寺","東京","杉並区高円寺"],"69":["タコリッコ 池袋","東京","豊島区池袋"],"70":["EL TORITO 赤坂","東京","港区赤坂"],"71":["PEDRITO 三田","東京","港区三田"],"72":["月島タコスバー","東京","中央区月島"],"73":["PUEBLA 神楽坂","東京","新宿区神楽坂"],"74":["メキシコ居酒屋 ソルアミーゴ 新橋","東京","港区新橋"],"75":["EL PANCHO 大阪・天王寺","大阪","阿倍野区天王寺"],"76":["メキシカーナ 大阪・天満橋","大阪","中央区天満橋"],"77":["TACOS LOCOS 大阪・アメ村","大阪","中央区アメ村"],"78":["Taco Bell 道頓堀店","大阪","中央区道頓堀"],"79":["El Coyot4 京都・河原町","京都","下京区河原町"],"80":["タコスバル FIESTA 京都・三条","京都","中京区三条"],"81":["Los Amigos 神戸・元町","兵庫","中央区元町"],"82":["EL SOL 神戸・北野","兵庫","中央区北野"],"83":["タコリア 奈良","奈良","奈良市奈良町"],"84":["メキシカンダイナー マチャカド 滋賀・草津","滋賀","草津市"],"85":["JERRY","愛知","中区大須"],"86":["Hot Spice MUCHO CHICKEN 名古屋・栄","愛知","中区栄"],"87":["タコスバー AMIGO 静岡","静岡","静岡市葵区"],"88":["メキシカンキッチン エルソル 浜松","静岡","浜松市中区"],"89":["タコス＆バー FIESTA 金沢","石川","金沢市香林坊"],"90":["Don Tacos 仙台・木町通","宮城","仙台市青葉区木町通"],"91":["メキシカングリル CALIENTE 仙台・国分町","宮城","仙台市青葉区国分町"],"92":["TACO LIBRE 山形","山形","山形市城南町"],"93":["タコスバー サルサ 新潟","新潟","新潟市中央区"],"94":["タコスカフェ リンダ 盛岡","岩手","盛岡市中央通"],"95":["メキシカンダイナー ロコ 岡山","岡山","岡山市北区"],"96":["タコスバル アミーゴ 高松","香川","高松市"],"97":["EL MARIACHI 松山","愛媛","松山市中央"],"98":["タコスハウス ブエノ 広島・流川","広島","中央区流川"],"99":["メキシカンカフェ サボテン 徳島","徳島","徳島市"],"100":["琉球多幸寿 福岡店 天神","福岡","中央区天神"],"101":["タコスバー チェラス 福岡・大名","福岡","中央区大名"],"102":["メキシカンキッチン パンチョ 北九州","福岡","北九州市小倉北区"],"103":["El Camino 熊本・上通","熊本","中央区上通"],"104":["タコスハウス ソル 鹿児島・天文館","鹿児島","天文館"],"105":["メキシカンバル コヨーテ 長崎・浜町","長崎","中央区浜町"],"106":["タコスカフェ マヤ 宮崎","宮崎","宮崎市高千穂通"],"107":["メキシカンダイニング サルサ 大分","大分","大分市"],"108":["キングタコス 長田店 那覇","沖縄","那覇市長田"],"109":["SENOR TACO 沖縄市","沖縄","沖縄市"],"110":["BORRACHOS 那覇・国際通り","沖縄","那覇市国際通り"],"111":["タコス屋 パンチョ 北谷","沖縄","北谷町"],"112":["メキシカンフード ルチャ 読谷","沖縄","読谷村"],"113":["タコスパーラー サンセット 恩納村","沖縄","恩納村"],"114":["キングタコス 普天間店 宜野湾","沖縄","宜野湾市普天間"],"115":["Verde Fresco","東京","中野区"],"116":["Locoバル","東京","渋谷区"],"117":["メヒコキッチン","東京","千代田区"],"118":["Solカフェ","東京","墨田区"],"119":["コヨーテ亭","東京","台東区"],"120":["Sol Bueno","東京","文京区"],"121":["タコスのスタンド","東京","吉祥寺"],"122":["Verde Chili","東京","中野区"],"123":["メヒコダイナー","東京","中野区"],"124":["Fiesta食堂","東京","墨田区"],"125":["ワカモレハウス","東京","新宿区"],"126":["Dorado Mexico","東京","江東区"],"127":["Dorado Chili","東京","北区"],"128":["Libreファクトリー","東京","品川区"],"129":["アミーゴカフェ","東京","練馬区"],"130":["Taco食堂","東京","中央区"],"131":["Burritoガレージ","東京","中央区"],"132":["Fresco Sol","東京","町田"],"133":["サルサのガレージ","東京","江東区"],"134":["Casa工房","東京","千代田区"],"135":["ワカモレラボ","東京","杉並区"],"136":["Sol Mexico","東京","新宿区"],"137":["Verde Viva","東京","吉祥寺"],"138":["Amigoガレージ","東京","大田区"],"139":["Frescoバル","東京","台東区"],"140":["Taco Taco","東京","北区"],"141":["Tacoダイナー","東京","港区"],"142":["Viva Amigo","東京","北区"],"143":["Taco工房","東京","文京区"],"144":["Amigo工房","東京","港区"],"145":["Loco Azul","東京","町田"],"146":["ティエラ亭","東京","杉並区"],"147":["Salsaカフェ","東京","世田谷区"],"148":["Amigo家","東京","新宿区"],"149":["Mexico Dorado","東京","大田区"],"150":["Sol工房","東京","杉並区"],"151":["Buenoダイナー","東京","世田谷区"],"152":["Viva Mexico","東京","目黒区"],"153":["Rojoハウス","東京","目黒区"],"154":["ハバネロの亭","東京","港区"],"155":["Amigoファクトリー","東京","中野区"],"156":["メヒコバル","東京","大田区"],"157":["カサの工房","東京","足立区"],"158":["Locoダイナー","東京","目黒区"],"159":["Solキッチン","東京","板橋区"],"160":["Taco Salsa","東京","中央区"],"161":["Fiesta Libre","東京","品川区"],"162":["Frescoスタンド","東京","北区"],"163":["Dorado堂","東京","足立区"],"164":["ソルスタンド","東京","文京区"],"165":["Amigo Taco","大阪","城東"],"166":["リオダイナー","大阪","心斎橋"],"167":["Fuego Luna","大阪","梅田"],"168":["Mexico食堂","大阪","都島"],"169":["Azulガレージ","大阪","住吉"],"170":["Libre亭","大阪","堀江"],"171":["Viva Azul","大阪","堀江"],"172":["Burrito Libre","大阪","城東"],"173":["マールファクトリー","大阪","住吉"],"174":["Amigoダイナー","大阪","梅田"],"175":["プラヤダイナー","大阪","城東"],"176":["Fresco Azul","大阪","天王寺"],"177":["Amigo Mexico","大阪","都島"],"178":["サルサの家","大阪","住吉"],"179":["Fiesta家","大阪","堀江"],"180":["Luna Azul","大阪","都島"],"181":["Taco Chili","大阪","阿倍野"],"182":["Viva Dorado","大阪","堀江"],"183":["Chili Viva","大阪","福島"],"184":["ソルファクトリー","大阪","住吉"],"185":["カサガレージ","大阪","梅田"],"186":["Salsa Chili","大阪","福島"],"187":["Loco Fiesta","大阪","難波"],"188":["Casa Dorado","大阪","心斎橋"],"189":["Rojo食堂","大阪","城東"],"190":["Loco Rojo","神奈川","藤沢"],"191":["Mexicoキッチン","神奈川","鎌倉"],"192":["Verde亭","神奈川","鎌倉"],"193":["Sol Luna","神奈川","横浜元町"],"194":["Salsa Mexico","神奈川","みなとみらい"],"195":["Chiliラボ","神奈川","みなとみらい"],"196":["Sol屋","神奈川","横浜元町"],"197":["Viva Burrito","神奈川","鎌倉"],"198":["Dorado Fuego","神奈川","みなとみらい"],"199":["Burrito Dorado","神奈川","横須賀"],"200":["Sol Sol","神奈川","藤沢"],"201":["Burrito Rojo","神奈川","川崎"],"202":["Casa堂","愛知","今池"],"203":["メヒコのキッチン","愛知","今池"],"204":["メヒコのガレージ","愛知","名駅"],"205":["Viva食堂","愛知","東桜"],"206":["Fiesta工房","愛知","名駅"],"207":["ブリトー屋","愛知","岡崎"],"208":["チリダイナー","愛知","一宮"],"209":["Loco堂","愛知","一宮"],"210":["シエロのダイナー","愛知","豊田"],"211":["Amigo Salsa","愛知","名駅"],"212":["Verde屋","愛知","一宮"],"213":["Frescoラボ","愛知","名駅"],"214":["Libre Burrito","愛知","東桜"],"215":["Frescoハウス","愛知","今池"],"216":["Burrito Chili","愛知","今池"],"217":["Rojoダイナー","福岡","中洲"],"218":["ブリトーラボ","福岡","中洲"],"219":["フエゴのスタンド","福岡","糸島"],"220":["Amigo屋","福岡","西新"],"221":["Azul工房","福岡","久留米"],"222":["Bueno工房","福岡","糸島"],"223":["Casa家","福岡","糸島"],"224":["Rojo屋","福岡","小倉"],"225":["Luna家","福岡","箱崎"],"226":["Rojo Loco","福岡","久留米"],"227":["Casaキッチン","福岡","小倉"],"228":["タコス堂","福岡","糸島"],"229":["Fuegoスタンド","京都","北山"],"230":["Mexico Chili","京都","嵐山"],"231":["Libre堂","京都","伏見"],"232":["Salsa Salsa","京都","河原町"],"233":["コヨーテ堂","京都","北山"],"234":["プラヤの工房","京都","伏見"],"235":["タコスカフェ","京都","四条"],"236":["Fiesta Sol","京都","伏見"],"237":["Salsa堂","京都","伏見"],"238":["マールの堂","京都","北山"],"239":["コヨーテの家","北海道","函館"],"240":["ハバネロのスタンド","北海道","帯広"],"241":["Sol亭","北海道","北24条"],"242":["Burrito Taco","北海道","函館"],"243":["Azulラボ","北海道","帯広"],"244":["Chili Fuego","北海道","函館"],"245":["Fuegoキッチン","北海道","函館"],"246":["Casaカフェ","北海道","旭川"],"247":["Amigo Loco","北海道","北24条"],"248":["Amigo Sol","北海道","函館"],"249":["Mexico Libre","沖縄","宜野湾"],"250":["Mexico Viva","沖縄","コザ"],"251":["Fiesta屋","沖縄","北谷"],"252":["Salsaハウス","沖縄","コザ"],"253":["Chiliバル","沖縄","宜野湾"],"254":["ティエラのファクトリー","沖縄","コザ"],"255":["リオ家","沖縄","名護"],"256":["Casa Verde","沖縄","宜野湾"],"257":["Luna屋","沖縄","国際通り"],"258":["Azulスタンド","沖縄","牧志"],"259":["Casa亭","兵庫","姫路"],"260":["Verde Luna","兵庫","明石"],"261":["シエロのバル","兵庫","明石"],"262":["Salsaスタンド","兵庫","灘"],"263":["マールガレージ","兵庫","尼崎"],"264":["エストレーヤのラボ","兵庫","西宮"],"265":["Casa Fuego","兵庫","尼崎"],"266":["Casaスタンド","兵庫","尼崎"],"267":["Luna食堂","宮城","国分町"],"268":["サルサの工房","宮城","国分町"],"269":["Loco食堂","宮城","宮城野"],"270":["Viva Viva","宮城","石巻"],"271":["ソルラボ","宮城","国分町"],"272":["Taco Viva","広島","福山"],"273":["Salsa Viva","広島","呉"],"274":["Vivaハウス","広島","本通り"],"275":["チリのスタンド","広島","本通り"],"276":["Frescoカフェ","広島","本通り"],"277":["Bueno Libre","千葉","浦安"],"278":["Fiesta Dorado","千葉","千葉"],"279":["マールキッチン","千葉","浦安"],"280":["Azul Bueno","千葉","柏"],"281":["Verde家","千葉","浦安"],"282":["Chiliダイナー","埼玉","浦和"],"283":["コヨーテ工房","埼玉","浦和"],"284":["Taco堂","埼玉","大宮"],"285":["Burrito Salsa","埼玉","川越"],"286":["Fuegoハウス","埼玉","川口"],"287":["ブリトーのダイナー","静岡","葵区"],"288":["Chiliカフェ","静岡","浜松"],"289":["Mexicoカフェ","静岡","浜松"],"290":["Viva Taco","奈良","橿原"],"291":["アミーゴガレージ","奈良","橿原"],"292":["Libre屋","石川","近江町"],"293":["コヨーテのガレージ","石川","片町"],"294":["エストレーヤファクトリー","新潟","万代"],"295":["Dorado亭","新潟","長岡"],"296":["Chili Rojo","長野","長野"],"297":["Libre Loco","長野","松本"],"298":["シエロのカフェ","群馬","前橋"],"299":["Chili亭","栃木","宇都宮"],"300":["ティエラの工房","茨城","水戸"],"301":["Fiestaハウス","三重","津"],"302":["Sol堂","岐阜","岐阜"],"303":["Fresco堂","和歌山","和歌山"],"304":["ティエラ食堂","山口","下関"],"305":["Bueno Dorado","佐賀","佐賀"],"306":["Bueno Azul","大分","大分"],"307":["サルサ屋","滋賀","大津"],"308":["Viva Fiesta","岩手","盛岡"],"309":["Tacoファクトリー","山形","山形"],"310":["カサの家","富山","富山"],"311":["Luna Sol","福島","郡山"],"312":["マール食堂","秋田","秋田"],"313":["カサバル","青森","青森"],"314":["Rojo Luna","香川","高松"],"315":["Mexico Sol","愛媛","松山"],"316":["Chili家","高知","高知"],"317":["Taco Libre","徳島","徳島"],"318":["ルナラボ","熊本","熊本"],"319":["Dorado屋","鹿児島","天文館"],"320":["ハバネロスタンド","長崎","浜町"],"321":["ワカモレのキッチン","宮崎","宮崎"],"322":["メキシカンバル RICO","千葉","船橋"],"323":["JAM TREE JAMMIN","千葉","千葉中央"],"324":["海辺のタコス屋 sachi-ta","千葉","長生村"],"325":["TAQUITO 市川店","千葉","市川"],"326":["38TACOS","千葉","千葉中央"],"327":["CAFE","千葉","千葉中央"],"328":["TACO GLAMP","千葉","一宮"],"329":["DESPERADO","千葉","千葉中央"],"330":["TOPA TACOS","千葉","一宮"],"331":["チランガバンダ","埼玉","桶川"],"332":["ロスボラチョス","埼玉","薕"],"333":["Mexican Dining Hana-Hana","埼玉","熊谷"],"334":["KITADE TACOS 深谷花園店","埼玉","深谷"],"335":["パンチラインガレージ","埼玉","川越"],"336":["Hachidori","埼玉","上尾"],"337":["エル・リンコン","埼玉","所沢"],"338":["タコス・デ・ソル","埼玉","越谷"],"339":["カサ・デ・アミーゴ","埼玉","草加"],"340":["ラ・フロンテラ","埼玉","志木"],"341":["TACOS PEPE","富山","富山市婦中町"],"342":["tacos y margarita","山形","山形市本町"],"343":["アスタコス","佐賀","佐賀市神野東"],"344":["フリーダム タコス ベース","岡山","岡山市中区竹田"],"345":["トランキーロタコス 父母ヶ浜店","香川","三豊市仁尾町"],"346":["SANBARCO","宮崎","宮崎市青島"],"347":["テキラッチョ","大分","大分市大手町"],"348":["HOLA! TACOS","岩手","山田町織笠"],"349":["メシカ","和歌山","和歌山市新中通"],"350":["Mexican Comedor gurico","福島","福島市"],"351":["non's TACOS","福島","福島市"],"352":["メキシカンキッチン・バルバ","茨城","古河市"],"353":["Thunder Tacos","栃木","宇都宮市"],"354":["メキシカン酒場 MUCHO AMIGO","静岡","浜松市中央区"],"355":["覇王樹（サボテン）","大阪","大阪市西区北堀江"],"356":["CANTINA RIMA","大阪","大阪市北区中崎町"],"357":["TACOstore 森","兵庫","加古川市"],"358":["dos tacos yasaka","京都","京都市東山区"],"359":["メキシコ料理 ロシータ","福岡","福岡市博多区中洲"],"360":["TACOMIA","福岡","福岡市中央区大手門"],"361":["メキシコレストラン トルタコス","熊本","熊本市"],"362":["El Dorado","長崎","長崎市"],"363":["ELtope","北海道","札幌市中央区大通"],"364":["Burrito y Tacos 5884","長野","上伊那郡箕輪町"],"365":["TACO FANATICO 久屋大通店","名古屋","名古屋市中区"],"366":["創作メキシコ料理 チャベリータ","三重","津市久居"],"367":["LUCKY TACOS","沖縄","那覇市平和通り"],"368":["赤とんぼ","沖縄","那覇市"],"369":["ONI TACO 池袋店","東京","豊島区南池袋"],"370":["ニコのタコス","東京","豊島区西池袋"],"371":["tacos trap'","東京","新宿区新宿御苑前"],"372":["カーサテキーラ Tokyo","東京","新宿区歌舞伎町"],"373":["Mexican Dining AVOCADO","東京","新宿区新宿三丁目"],"374":["EL CARACOL","東京","新宿区四谷三丁目"],"375":["WIRED TACOS CLUB TOKYO","東京","港区高輪（品川駅）"],"376":["FONDA MEXICANA New York","東京","中央区銀座"],"377":["TACO RICO 大手町ビル店","東京","千代田区大手町"],"378":["ヒゲタコス","東京","足立区北千住"],"379":["タコスビーム","東京","板橋区上板橋"],"380":["EL-POCO","東京","板橋区志村坂上"],"381":["3Bタコス","東京","台東区田原町"]}
